strime/__init__.py
strime/main.py
strime-1.0.3.dist-info/LICENSE
strime-1.0.3.dist-info/METADATA
strime-1.0.3.dist-info/WHEEL
strime-1.0.3.dist-info/top_level.txt
strime-1.0.3.dist-info/RECORD
