Metadata-Version: 2.1
Name: strime
Version: 1.0.3
Summary: A simple string (time+unit) to seconds converter.
Home-page: https://github.com/woidzero/strime
Author: woidzero
Author-email: woidzeroo@gmail.com
License: MIT License
License-File: LICENSE
